vtiger_cloudsdk_restapi/__init__.py
vtiger_cloudsdk_restapi-0.0.0.dist-info/DESCRIPTION.rst
vtiger_cloudsdk_restapi-0.0.0.dist-info/METADATA
vtiger_cloudsdk_restapi-0.0.0.dist-info/RECORD
vtiger_cloudsdk_restapi-0.0.0.dist-info/WHEEL
vtiger_cloudsdk_restapi-0.0.0.dist-info/metadata.json
vtiger_cloudsdk_restapi-0.0.0.dist-info/top_level.txt
